psqlomni/__init__.py
psqlomni/__main__.py
psqlomni-0.1.2.dist-info/METADATA
psqlomni-0.1.2.dist-info/WHEEL
psqlomni-0.1.2.dist-info/entry_points.txt
psqlomni-0.1.2.dist-info/RECORD
