Metadata-Version: 2.1
Name: psqlomni
Version: 0.1.2
Summary: LLM-powered chat interface to your Postgres database - (psql powered with Natural Language)
Author: emmakodes
Author-email: emmamichael65@gmail.com
Requires-Python: >=3.9,<4.0
Classifier: Programming Language :: Python :: 3
Classifier: Programming Language :: Python :: 3.9
Classifier: Programming Language :: Python :: 3.10
Classifier: Programming Language :: Python :: 3.11
Requires-Dist: halo (>=0.0.31,<0.0.32)
Requires-Dist: langchain (>=0.1.20,<0.2.0)
Requires-Dist: langchain-community (>=0.0.38,<0.0.39)
Requires-Dist: langchain-openai (>=0.1.7,<0.2.0)
Requires-Dist: prompt-toolkit (>=3.0.43,<4.0.0)
Requires-Dist: psycopg2 (>=2.9.9,<3.0.0)
Requires-Dist: toml (>=0.10.2,<0.11.0)
